threemystic_cloud_data_client/__main__.py
threemystic_cloud_data_client/__version__.py
threemystic_cloud_data_client/cloud_data_client.py
threemystic_cloud_data_client/cli/__init__.py
threemystic_cloud_data_client/cli/actions/base_class/base.py
threemystic_cloud_data_client/cli/actions/config/__init__.py
threemystic_cloud_data_client/cloud_providers/aws/__init__.py
threemystic_cloud_data_client/cloud_providers/aws/base_class/base.py
threemystic_cloud_data_client/cloud_providers/aws/client/__init__.py
threemystic_cloud_data_client/cloud_providers/aws/client/actions/budget.py
threemystic_cloud_data_client/cloud_providers/aws/client/actions/certificates.py
threemystic_cloud_data_client/cloud_providers/aws/client/actions/clouddb.py
threemystic_cloud_data_client/cloud_providers/aws/client/actions/cloudstorage.py
threemystic_cloud_data_client/cloud_providers/aws/client/actions/database.py
threemystic_cloud_data_client/cloud_providers/aws/client/actions/datawarehouse.py
threemystic_cloud_data_client/cloud_providers/aws/client/actions/dns.py
threemystic_cloud_data_client/cloud_providers/aws/client/actions/elastisearch.py
threemystic_cloud_data_client/cloud_providers/aws/client/actions/function.py
threemystic_cloud_data_client/cloud_providers/aws/client/actions/memorydb.py
threemystic_cloud_data_client/cloud_providers/aws/client/actions/storage.py
threemystic_cloud_data_client/cloud_providers/aws/client/actions/vm.py
threemystic_cloud_data_client/cloud_providers/aws/client/actions/vmimage.py
threemystic_cloud_data_client/cloud_providers/aws/client/actions/vmss.py
threemystic_cloud_data_client/cloud_providers/aws/client/actions/base_class/base.py
threemystic_cloud_data_client/cloud_providers/aws/config/step_1.py
threemystic_cloud_data_client/cloud_providers/aws/config/base_class/base.py
threemystic_cloud_data_client/cloud_providers/azure/__init__.py
threemystic_cloud_data_client/cloud_providers/azure/base_class/base.py
threemystic_cloud_data_client-0.1.89.dist-info/METADATA
threemystic_cloud_data_client-0.1.89.dist-info/WHEEL
threemystic_cloud_data_client-0.1.89.dist-info/entry_points.txt
threemystic_cloud_data_client-0.1.89.dist-info/licenses/LICENSE
threemystic_cloud_data_client-0.1.89.dist-info/RECORD
