Metadata-Version: 2.1
Name: threemystic-cloud-data-client
Version: 0.1.89
Summary: A tool for collecting data from various cloud providers
Project-URL: Homepage, https://github.com/3MysticApes/3mystic_cloud_data_client
Project-URL: Bug Tracker, https://github.com/3MysticApes/3mystic_cloud_data_client/issues
Author: Ron Truex
License-Expression: MIT
License-File: LICENSE
Classifier: License :: OSI Approved :: MIT License
Classifier: Natural Language :: English
Classifier: Operating System :: OS Independent
Classifier: Programming Language :: Python :: 3.8
Classifier: Programming Language :: Python :: 3.9
Classifier: Programming Language :: Python :: 3.10
Classifier: Programming Language :: Python :: 3.11
Classifier: Programming Language :: Python :: Implementation :: CPython
Classifier: Programming Language :: Python :: Implementation :: PyPy
Requires-Python: >=3.8
Requires-Dist: asyncio>=3.4.3
Requires-Dist: azure-keyvault-administration>=4
Requires-Dist: azure-keyvault-certificates>=4
Requires-Dist: azure-keyvault-keys>=4
Requires-Dist: azure-keyvault-secrets>=4
Requires-Dist: azure-mgmt-compute>=29
Requires-Dist: azure-mgmt-cosmosdb>=9
Requires-Dist: azure-mgmt-costmanagement>=4
Requires-Dist: azure-mgmt-dns>=8
Requires-Dist: azure-mgmt-keyvault>=10
Requires-Dist: azure-mgmt-managementgroups>=1
Requires-Dist: azure-mgmt-monitor>=5
Requires-Dist: azure-mgmt-network>=23
Requires-Dist: azure-mgmt-privatedns>=1
Requires-Dist: azure-mgmt-rdbms>=10
Requires-Dist: azure-mgmt-redis>=14
Requires-Dist: azure-mgmt-resourcegraph>=8
Requires-Dist: azure-mgmt-sql>=3
Requires-Dist: azure-mgmt-sqlvirtualmachine>=0.6
Requires-Dist: azure-mgmt-subscription>=3
Requires-Dist: azure-mgmt-synapse>=2
Requires-Dist: colorama; platform_system == 'Windows'
Requires-Dist: threemystic-cloud-client>=0.1.63
Requires-Dist: threemystic-common>=0.1.17
Requires-Dist: tqdm>=4.65.0
Requires-Dist: typing-extensions>=4.4.0
